cronlog-stubs/METADATA.toml
cronlog-stubs/__init__.pyi
cronlog-stubs/py.typed
crontab-stubs/METADATA.toml
crontab-stubs/__init__.pyi
crontab-stubs/py.typed
crontabs-stubs/METADATA.toml
crontabs-stubs/__init__.pyi
crontabs-stubs/py.typed
types_python_crontab-3.3.0.20250715.dist-info/licenses/LICENSE
types_python_crontab-3.3.0.20250715.dist-info/METADATA
types_python_crontab-3.3.0.20250715.dist-info/WHEEL
types_python_crontab-3.3.0.20250715.dist-info/top_level.txt
types_python_crontab-3.3.0.20250715.dist-info/RECORD
